chemcloud/__init__.py
chemcloud/client.py
chemcloud/config.py
chemcloud/exceptions.py
chemcloud/http_client.py
chemcloud/models.py
chemcloud/py.typed
chemcloud-0.16.0.dist-info/LICENSE
chemcloud-0.16.0.dist-info/METADATA
chemcloud-0.16.0.dist-info/WHEEL
chemcloud-0.16.0.dist-info/RECORD
