Metadata-Version: 2.3
Name: chemcloud
Version: 0.16.0
Summary: Fast, secure, scalable quantum chemistry. A Python client for the the ChemCloud server.
License: MIT
Author: Colton Hicks
Author-email: github@coltonhicks.com
Requires-Python: >=3.9,<4.0
Classifier: Intended Audience :: Science/Research
Classifier: License :: OSI Approved :: MIT License
Classifier: Operating System :: OS Independent
Classifier: Programming Language :: Python
Classifier: Programming Language :: Python :: 3
Classifier: Programming Language :: Python :: 3.9
Classifier: Programming Language :: Python :: 3.10
Classifier: Programming Language :: Python :: 3.11
Classifier: Programming Language :: Python :: 3.12
Classifier: Programming Language :: Python :: 3.13
Classifier: Programming Language :: Python :: 3 :: Only
Classifier: Topic :: Software Development
Classifier: Topic :: Software Development :: Libraries
Classifier: Topic :: Software Development :: Libraries :: Python Modules
Classifier: Typing :: Typed
Requires-Dist: httpx (>=0.27)
Requires-Dist: pydantic (>=2.0.0,!=2.4.0)
Requires-Dist: pydantic-settings (>=2.0.3,<3.0.0)
Requires-Dist: qcio (>=0.11.0)
Requires-Dist: tomli (>=2.0,<3.0) ; python_version < "3.11"
Requires-Dist: tomli-w (>=1.0.0,<2.0.0)
Project-URL: Documentation, https://mtzgroup.github.io/chemcloud-client/
Project-URL: Homepage, https://mtzgroup.github.io/chemcloud-client/
Project-URL: Repository, https://github.com/mtzgroup/chemcloud-client
